foodx_backup_source/VERSION
foodx_backup_source/__init__.py
foodx_backup_source/_default_values.py
foodx_backup_source/_file_io.py
foodx_backup_source/_hash.py
foodx_backup_source/_main.py
foodx_backup_source/_snapshot.py
foodx_backup_source/_version.py
foodx_backup_source/azure.py
foodx_backup_source/entrypoint.py
foodx_backup_source/py.typed
foodx_backup_source/schema.py
foodx_backup_source-0.2.1.post1.dist-info/entry_points.txt
foodx_backup_source-0.2.1.post1.dist-info/LICENSE
foodx_backup_source-0.2.1.post1.dist-info/WHEEL
foodx_backup_source-0.2.1.post1.dist-info/METADATA
foodx_backup_source-0.2.1.post1.dist-info/RECORD
